chineserand/__init__.py
chineserand/global_word.rst
chineserand/sentences.rst
chineserand-0.0.4.dist-info/LICENSE
chineserand-0.0.4.dist-info/METADATA
chineserand-0.0.4.dist-info/WHEEL
chineserand-0.0.4.dist-info/top_level.txt
chineserand-0.0.4.dist-info/RECORD
