Metadata-Version: 2.2
Name: chineserand
Version: 0.0.4
Summary: 随机生成中文字符工具包
Author-email: chenzuoli <chenzuoli709@163.com>
Project-URL: Homepage, https://github.com/chenzuoli/chineserand
Project-URL: Issues, https://github.com/chenzuoli/chineserand/issues
Classifier: Programming Language :: Python :: 3
Classifier: License :: OSI Approved :: MIT License
Classifier: Operating System :: OS Independent
Requires-Python: >=3.0
License-File: LICENSE
